bgpvpn_dashboard/__init__.py
bgpvpn_dashboard/api/__init__.py
bgpvpn_dashboard/api/bgpvpn.py
bgpvpn_dashboard/common/__init__.py
bgpvpn_dashboard/common/bgpvpn.py
bgpvpn_dashboard/dashboards/__init__.py
bgpvpn_dashboard/dashboards/admin/__init__.py
bgpvpn_dashboard/dashboards/admin/bgpvpn/__init__.py
bgpvpn_dashboard/dashboards/admin/bgpvpn/forms.py
bgpvpn_dashboard/dashboards/admin/bgpvpn/panel.py
bgpvpn_dashboard/dashboards/admin/bgpvpn/tables.py
bgpvpn_dashboard/dashboards/admin/bgpvpn/tabs.py
bgpvpn_dashboard/dashboards/admin/bgpvpn/urls.py
bgpvpn_dashboard/dashboards/admin/bgpvpn/views.py
bgpvpn_dashboard/dashboards/admin/bgpvpn/workflows.py
bgpvpn_dashboard/dashboards/admin/bgpvpn/templates/bgpvpn/_create.html
bgpvpn_dashboard/dashboards/admin/bgpvpn/templates/bgpvpn/_detail_overview.html
bgpvpn_dashboard/dashboards/admin/bgpvpn/templates/bgpvpn/create.html
bgpvpn_dashboard/dashboards/project/__init__.py
bgpvpn_dashboard/dashboards/project/bgpvpn/__init__.py
bgpvpn_dashboard/dashboards/project/bgpvpn/forms.py
bgpvpn_dashboard/dashboards/project/bgpvpn/panel.py
bgpvpn_dashboard/dashboards/project/bgpvpn/tables.py
bgpvpn_dashboard/dashboards/project/bgpvpn/tabs.py
bgpvpn_dashboard/dashboards/project/bgpvpn/urls.py
bgpvpn_dashboard/dashboards/project/bgpvpn/views.py
bgpvpn_dashboard/dashboards/project/bgpvpn/workflows.py
bgpvpn_dashboard/dashboards/project/bgpvpn/network_associations/__init__.py
bgpvpn_dashboard/dashboards/project/bgpvpn/network_associations/tables.py
bgpvpn_dashboard/dashboards/project/bgpvpn/network_associations/tabs.py
bgpvpn_dashboard/dashboards/project/bgpvpn/network_associations/urls.py
bgpvpn_dashboard/dashboards/project/bgpvpn/network_associations/views.py
bgpvpn_dashboard/dashboards/project/bgpvpn/router_associations/__init__.py
bgpvpn_dashboard/dashboards/project/bgpvpn/router_associations/forms.py
bgpvpn_dashboard/dashboards/project/bgpvpn/router_associations/tables.py
networking_bgpvpn-23.0.0.dist-info/AUTHORS
networking_bgpvpn-23.0.0.dist-info/LICENSE
networking_bgpvpn-23.0.0.dist-info/METADATA
networking_bgpvpn-23.0.0.dist-info/WHEEL
networking_bgpvpn-23.0.0.dist-info/entry_points.txt
networking_bgpvpn-23.0.0.dist-info/pbr.json
networking_bgpvpn-23.0.0.dist-info/top_level.txt
networking_bgpvpn-23.0.0.dist-info/RECORD
