Metadata-Version: 2.1
Name: networking-bgpvpn
Version: 23.0.0
Summary: API and Framework to interconnect bgpvpn to neutron networks
Home-page: https://docs.openstack.org/networking-bgpvpn/latest/
Author: OpenStack
Author-email: openstack-discuss@lists.openstack.org
Classifier: Environment :: OpenStack
Classifier: Intended Audience :: Information Technology
Classifier: Intended Audience :: System Administrators
Classifier: License :: OSI Approved :: Apache Software License
Classifier: Operating System :: POSIX :: Linux
Classifier: Programming Language :: Python
Classifier: Programming Language :: Python :: Implementation :: CPython
Classifier: Programming Language :: Python :: 3 :: Only
Classifier: Programming Language :: Python :: 3
Classifier: Programming Language :: Python :: 3.10
Classifier: Programming Language :: Python :: 3.11
Classifier: Programming Language :: Python :: 3.12
Requires-Python: >=3.10
License-File: LICENSE
License-File: AUTHORS
Requires-Dist: pbr>=4.0.0
Requires-Dist: oslo.config>=5.2.0
Requires-Dist: oslo.db>=4.37.0
Requires-Dist: oslo.i18n>=3.15.3
Requires-Dist: oslo.log>=3.36.0
Requires-Dist: oslo.utils>=3.33.0
Requires-Dist: neutron-lib>=1.30.0
Requires-Dist: debtcollector>=1.19.0
Requires-Dist: neutron>=23.0.0.0b2
Provides-Extra: bagpipe
Requires-Dist: networking-bagpipe>=12.0.0; extra == "bagpipe"
Provides-Extra: horizon
Requires-Dist: horizon>=17.1.0; extra == "horizon"
Provides-Extra: test
Requires-Dist: hacking<6.2.0,>=6.1.0; extra == "test"
Requires-Dist: coverage!=4.4,>=4.0; extra == "test"
Requires-Dist: psycopg2>=2.8.5; extra == "test"
Requires-Dist: PyMySQL>=0.7.6; extra == "test"
Requires-Dist: WebOb>=1.8.2; extra == "test"
Requires-Dist: oslotest>=3.2.0; extra == "test"
Requires-Dist: pytest>=5.3.5; extra == "test"
Requires-Dist: stestr>=1.0.0; extra == "test"
Requires-Dist: testresources>=2.0.0; extra == "test"
Requires-Dist: testscenarios>=0.4; extra == "test"
Requires-Dist: testtools>=2.2.0; extra == "test"
Requires-Dist: tempest>=17.1.0; extra == "test"
Requires-Dist: isort==4.3.21; extra == "test"
Requires-Dist: networking-bagpipe>=12.0.0.0; extra == "test"
Requires-Dist: horizon>=17.1.0; extra == "test"
Requires-Dist: WebTest>=2.0.27; extra == "test"
